yt2md.py
yt2md-1.0.0.dist-info/licenses/LICENSE
yt2md-1.0.0.dist-info/METADATA
yt2md-1.0.0.dist-info/WHEEL
yt2md-1.0.0.dist-info/entry_points.txt
yt2md-1.0.0.dist-info/top_level.txt
yt2md-1.0.0.dist-info/RECORD
